linkbot/__init__.py
linkbot/__stub.so
linkbot/_linkbot.so
linkbot/demo/__init__.py
linkbot/demo/_setDongleSerial.py
linkbot/demo/_setSerialId.py
linkbot/demo/accelerometerEvents.py
linkbot/demo/buttonEvents.py
linkbot/demo/drive.py
linkbot/demo/encoderEvents.py
linkbot/demo/encoderEvents2.py
linkbot/demo/getAccelerometerData.py
linkbot/demo/getJointAngles.py
linkbot/demo/getJointSpeeds.py
linkbot/demo/getLedColor.py
linkbot/demo/move.py
linkbot/demo/moveContinuous.py
linkbot/demo/moveJoint.py
linkbot/demo/moveSmoothTest.py
linkbot/demo/moveTest.py
linkbot/demo/multiThreadMoveJoint.py
linkbot/demo/setBuzzerFrequency.py
linkbot/demo/setJointSpeeds.py
linkbot/demo/tiltDrive.py
PyLinkbot-2.3.7.dist-info/DESCRIPTION.rst
PyLinkbot-2.3.7.dist-info/METADATA
PyLinkbot-2.3.7.dist-info/metadata.json
PyLinkbot-2.3.7.dist-info/RECORD
PyLinkbot-2.3.7.dist-info/top_level.txt
PyLinkbot-2.3.7.dist-info/WHEEL
