Metadata-Version: 2.0
Name: PyLinkbot
Version: 2.3.7
Summary: Barobo Linkbot package
Home-page: http://www.barobo.com
Author: David Ko
Author-email: david@barobo.com
License: GPL
Download-URL: http://wiki.linkbotlabs.com/wiki/Learning_Python_3_with_the_Linkbot/Downloads
Platform: UNKNOWN
